{
	"recipes": [
		{
			"name": "Spaghetti Carbonara",
			"description": "A simple Roman pasta dish with egg, cheese, pancetta, and pepper.",
			"ingredients": [
				"200g spaghetti",
				"100g pancetta",
				"2 large eggs",
				"50g parmesan cheese",
				"Black pepper",
				"Salt"
			],
			"time": {
				"prep": 10,
				"cook": 15
			}
		},
		{
			"name": "Classic Cheeseburger",
			"description": "Juicy beef burger with cheddar cheese on a toasted bun.",
			"ingredients": [
				"1 beef patty",
				"2 slices cheddar cheese",
				"1 hamburger bun",
				"Lettuce",
				"Tomato",
				"Pickles",
				"Ketchup",
				"Mustard"
			],
			"time": {
				"prep": 10,
				"cook": 8
			}
		},
		{
			"name": "Chicken Teriyaki",
			"description": "Japanese-style grilled chicken glazed with sweet soy-based sauce.",
			"ingredients": [
				"2 chicken thighs",
				"3 tbsp soy sauce",
				"2 tbsp mirin",
				"2 tbsp sake",
				"1 tbsp sugar"
			],
			"time": {
				"prep": 10,
				"cook": 20
			}
		},
		{
			"name": "Avocado Toast",
			"description": "Simple and healthy toast with mashed avocado.",
			"ingredients": [
				"2 slices sourdough bread",
				"1 ripe avocado",
				"Salt",
				"Black pepper",
				"Chili flakes (optional)",
				"Lemon juice"
			],
			"time": {
				"prep": 5,
				"cook": 3
			}
		},
		{
			"name": "Miso Soup",
			"description": "Traditional Japanese soup with tofu, seaweed, and miso paste.",
			"ingredients": [
				"3 cups dashi stock",
				"2 tbsp miso paste",
				"100g silken tofu",
				"2 tbsp wakame seaweed",
				"2 green onions"
			],
			"time": {
				"prep": 5,
				"cook": 15
			}
		},
		{
			"name": "Beef Tacos",
			"description": "Soft corn tortillas filled with seasoned ground beef.",
			"ingredients": [
				"200g ground beef",
				"1 packet taco seasoning",
				"6 corn tortillas",
				"Lettuce",
				"Sour cream",
				"Shredded cheese",
				"Salsa"
			],
			"time": {
				"prep": 10,
				"cook": 15
			}
		},
		{
			"name": "Tomato Basil Soup",
			"description": "Creamy soup made with ripe tomatoes and fresh basil.",
			"ingredients": [
				"500g ripe tomatoes",
				"1 onion",
				"2 garlic cloves",
				"500ml vegetable broth",
				"Fresh basil",
				"Salt and pepper",
				"Olive oil"
			],
			"time": {
				"prep": 10,
				"cook": 30
			}
		},
		{
			"name": "Shrimp Fried Rice",
			"description": "Stir-fried rice with shrimp, vegetables, and soy sauce.",
			"ingredients": [
				"2 cups cooked rice",
				"200g shrimp, peeled",
				"2 eggs",
				"1/2 cup peas and carrots",
				"3 tbsp soy sauce",
				"2 green onions"
			],
			"time": {
				"prep": 10,
				"cook": 15
			}
		},
		{
			"name": "Caprese Salad",
			"description": "Italian salad with fresh tomatoes, mozzarella, and basil.",
			"ingredients": [
				"2 ripe tomatoes",
				"125g fresh mozzarella",
				"Fresh basil leaves",
				"Olive oil",
				"Salt and pepper",
				"Balsamic glaze (optional)"
			],
			"time": {
				"prep": 5,
				"cook": 0
			}
		},
		{
			"name": "French Omelette",
			"description": "Classic smooth and tender omelette.",
			"ingredients": [
				"3 eggs",
				"1 tbsp butter",
				"Salt",
				"Pepper",
				"Fresh herbs (optional)"
			],
			"time": {
				"prep": 3,
				"cook": 5
			}
		}
	]
}
